atomicarray/__init__.py
atomicarray/int.cp311-win_amd64.pyd
atomicarray-0.0.1.dist-info/METADATA
atomicarray-0.0.1.dist-info/WHEEL
atomicarray-0.0.1.dist-info/top_level.txt
atomicarray-0.0.1.dist-info/RECORD
